nsls2_detector_handlers/__init__.py
nsls2_detector_handlers/_version.py
nsls2_detector_handlers/electrometer.py
nsls2_detector_handlers/germ.py
nsls2_detector_handlers/pizzabox.py
nsls2_detector_handlers/srx_flyscans.py
nsls2_detector_handlers/webcam.py
nsls2_detector_handlers/tests/__init__.py
nsls2_detector_handlers/tests/conftest.py
nsls2_detector_handlers/tests/test_examples.py
nsls2_detector_handlers-0.1.0.dist-info/AUTHORS.rst
nsls2_detector_handlers-0.1.0.dist-info/LICENSE
nsls2_detector_handlers-0.1.0.dist-info/METADATA
nsls2_detector_handlers-0.1.0.dist-info/WHEEL
nsls2_detector_handlers-0.1.0.dist-info/entry_points.txt
nsls2_detector_handlers-0.1.0.dist-info/top_level.txt
nsls2_detector_handlers-0.1.0.dist-info/RECORD
