Metadata-Version: 2.1
Name: nsls2-detector-handlers
Version: 0.1.0
Summary: Staging repo for handlers specific to NSLS-II
Home-page: https://github.com/bluesky/nsls2-detector-handlers
Author: Brookhaven National Laboratory
Author-email: dama@bnl.gov
License: BSD (3-clause)
Classifier: Development Status :: 2 - Pre-Alpha
Classifier: Natural Language :: English
Classifier: Programming Language :: Python :: 3
Requires-Python: >=3.6
License-File: LICENSE
License-File: AUTHORS.rst
Requires-Dist: h5py
Requires-Dist: numpy
Requires-Dist: pandas
Requires-Dist: tifffile
